{
  "credit": "Made with Blockbench",
  "parent": "builtin/entity",
  "texture_size": [
    64,
    64
  ],
  "display": {
    "thirdperson_righthand": {
      "rotation": [
        102,
        -1,
        0
      ],
      "translation": [
        -0.5,
        4.25,
        0
      ],
      "scale": [
        0.75,
        0.75,
        0.75
      ]
    },
    "thirdperson_lefthand": {
      "rotation": [
        98,
        180,
        0
      ],
      "translation": [
        0.25,
        4.25,
        0
      ]
    },
    "firstperson_righthand": {
      "rotation": [
        73,
        11,
        30
      ],
      "translation": [
        3,
        2.75,
        -5.25
      ]
    },
    "firstperson_lefthand": {
      "rotation": [
        73,
        -11,
        -128
      ],
      "translation": [
        1.75,
        3.75,
        -3.25
      ]
    },
    "gui": {
      "rotation": [
        90,
        7,
        -38
      ],
      "translation": [
        -1.25,
        0,
        0
      ]
    },
    "fixed": {
      "rotation": [
        -89,
        180,
        0
      ],
      "translation": [
        -0.25,
        -1.25,
        0
      ]
    }
  }
}